LICENSE
README.md
setup.py
DeezyMatch/DeezyMatch.py
DeezyMatch/__init__.py
DeezyMatch/candidateRanker.py
DeezyMatch/combineVecs.py
DeezyMatch/data_processing.py
DeezyMatch/rnn_networks.py
DeezyMatch/rnn_networks_MSE.py
DeezyMatch/utils.py
DeezyMatch/utils_candidate_ranker.py
DeezyMatch.egg-info/PKG-INFO
DeezyMatch.egg-info/SOURCES.txt
DeezyMatch.egg-info/dependency_links.txt
DeezyMatch.egg-info/entry_points.txt
DeezyMatch.egg-info/not-zip-safe
DeezyMatch.egg-info/requires.txt
DeezyMatch.egg-info/top_level.txt