Metadata-Version: 2.1
Name: DeezyMatch
Version: 1.3.0
Summary: A Flexible Deep Learning Approach to Fuzzy String Matching and Candidate Ranking
Home-page: https://github.com/Living-with-machines/DeezyMatch
Author: The LwM Development Team
License: MIT License
Download-URL: https://github.com/Living-with-machines/DeezyMatch/archive/master.zip
Keywords: Fuzzy String Matching,Deep Learning,NLP,Natural Language Processing,living with machines
Platform: OS Independent
Classifier: Development Status :: 3 - Alpha
Classifier: License :: OSI Approved :: MIT License
Classifier: Natural Language :: English
Classifier: Programming Language :: Python :: 3
Classifier: Programming Language :: Python :: 3.7
Classifier: Programming Language :: Python :: 3.8
Classifier: Intended Audience :: End Users/Desktop
Classifier: Intended Audience :: Developers
Classifier: Intended Audience :: Education
Classifier: Intended Audience :: Science/Research
Classifier: Operating System :: Unix
Classifier: Operating System :: Microsoft :: Windows
Classifier: Operating System :: MacOS
Classifier: Operating System :: OS Independent
Classifier: Topic :: Software Development
Classifier: Topic :: Software Development :: Libraries :: Python Modules
Classifier: Topic :: Scientific/Engineering :: Artificial Intelligence
Requires-Python: >=3.7
License-File: LICENSE
